CHANGES.txt
README.txt
buildout.cfg
setup.py
bootstrap/bootstrap.py
src/zope/__init__.py
src/zope.app.homefolder.egg-info/PKG-INFO
src/zope.app.homefolder.egg-info/SOURCES.txt
src/zope.app.homefolder.egg-info/dependency_links.txt
src/zope.app.homefolder.egg-info/namespace_packages.txt
src/zope.app.homefolder.egg-info/not-zip-safe
src/zope.app.homefolder.egg-info/requires.txt
src/zope.app.homefolder.egg-info/top_level.txt
src/zope/app/__init__.py
src/zope/app/homefolder/README.txt
src/zope/app/homefolder/SETUP.cfg
src/zope/app/homefolder/__init__.py
src/zope/app/homefolder/browser.py
src/zope/app/homefolder/configure.zcml
src/zope/app/homefolder/homefolder.pt
src/zope/app/homefolder/homefolder.py
src/zope/app/homefolder/i18n.py
src/zope/app/homefolder/interfaces.py
src/zope/app/homefolder/tests.py
src/zope/app/homefolder/zope.app.homefolder-configure.zcml